README.md
README.rst
setup.cfg
setup.py
pych/__init__.py
pych/catalog.py
pych/file.py
pych/post.py
pych/thread.py
pych.egg-info/PKG-INFO
pych.egg-info/SOURCES.txt
pych.egg-info/dependency_links.txt
pych.egg-info/requires.txt
pych.egg-info/top_level.txt