Metadata-Version: 1.0
Name: pych
Version: 1.0
Summary: Python 2ch API client.
Home-page: UNKNOWN
Author: BehindLoader
Author-email: UNKNOWN
License: MIT
Platform: UNKNOWN
